{"icons":[{"icon":"sharp-insert-link","svg":"<path d=\"M3.9 12c0-1.71 1.39-3.1 3.1-3.1h4V7H7c-2.76 0-5 2.24-5 5s2.24 5 5 5h4v-1.9H7c-1.71 0-3.1-1.39-3.1-3.1zM8 13h8v-2H8v2zm9-6h-4v1.9h4c1.71 0 3.1 1.39 3.1 3.1s-1.39 3.1-3.1 3.1h-4V17h4c2.76 0 5-2.24 5-5s-2.24-5-5-5z\" fill=\"currentColor\"/>","width":24,"height":24},{"icon":"sharp-insert-photo","svg":"<path d=\"M21 21V3H3v18h18zM8.5 13.5l2.5 3.01L14.5 12l4.5 6H5l3.5-4.5z\" fill=\"currentColor\"/>","width":24,"height":24},{"icon":"sharp-insights","svg":"<path d=\"M21 8c-1.45 0-2.26 1.44-1.93 2.51l-3.55 3.56c-.3-.09-.74-.09-1.04 0l-2.55-2.55C12.27 10.45 11.46 9 10 9c-1.45 0-2.27 1.44-1.93 2.52l-4.56 4.55C2.44 15.74 1 16.55 1 18c0 1.1.9 2 2 2c1.45 0 2.26-1.44 1.93-2.51l4.55-4.56c.3.09.74.09 1.04 0l2.55 2.55C12.73 16.55 13.54 18 15 18c1.45 0 2.27-1.44 1.93-2.52l3.56-3.55c1.07.33 2.51-.48 2.51-1.93c0-1.1-.9-2-2-2z\" fill=\"currentColor\"/><path d=\"M15 9l.94-2.07L18 6l-2.06-.93L15 3l-.92 2.07L12 6l2.08.93zM3.5 11L4 9l2-.5L4 8l-.5-2L3 8l-2 .5L3 9z\" fill=\"currentColor\"/>","width":24,"height":24},{"icon":"sharp-integration-instructions","svg":"<path d=\"M21 3h-6.18C14.4 1.84 13.3 1 12 1s-2.4.84-2.82 2H3v18h18V3zM11 14.17l-1.41 1.42L6 12l3.59-3.59L11 9.83L8.83 12L11 14.17zm1-9.92c-.41 0-.75-.34-.75-.75s.34-.75.75-.75s.75.34.75.75s-.34.75-.75.75zm2.41 11.34L13 14.17L15.17 12L13 9.83l1.41-1.42L18 12l-3.59 3.59z\" fill=\"currentColor\"/>","width":24,"height":24},{"icon":"sharp-invert-colors","svg":"<path d=\"M17.66 7.93L12 2.27L6.34 7.93c-3.12 3.12-3.12 8.19 0 11.31C7.9 20.8 9.95 21.58 12 21.58s4.1-.78 5.66-2.34c3.12-3.12 3.12-8.19 0-11.31zM12 19.59c-1.6 0-3.11-.62-4.24-1.76C6.62 16.69 6 15.19 6 13.59s.62-3.11 1.76-4.24L12 5.1v14.49z\" fill=\"currentColor\"/>","width":24,"height":24},{"icon":"sharp-invert-colors-off","svg":"<path d=\"M12 5.1v4.05l7.4 7.4c1.15-2.88.59-6.28-1.75-8.61L12 2.27L8.56 5.71l1.41 1.41L12 5.1zm-7.6-.73L2.99 5.78l2.78 2.78a8.003 8.003 0 0 0 .57 10.68A7.98 7.98 0 0 0 12 21.58c1.78 0 3.56-.59 5.02-1.77l2.7 2.7l1.41-1.41L4.4 4.37zM12 19.59c-1.6 0-3.11-.62-4.24-1.76A5.945 5.945 0 0 1 6 13.59c0-1.32.43-2.56 1.21-3.59L12 14.79v4.8z\" fill=\"currentColor\"/>","width":24,"height":24},{"icon":"sharp-iso","svg":"<path d=\"M21 3H3v18h18V3zM5.5 7.5h2v-2H9v2h2V9H9v2H7.5V9h-2V7.5zM19 19H5L19 5v14zm-2-2v-1.5h-5V17h5z\" fill=\"currentColor\"/>","width":24,"height":24},{"icon":"sharp-keyboard","svg":"<path d=\"M22 5H2.01L2 19h20V5zM11 8h2v2h-2V8zm0 3h2v2h-2v-2zM8 8h2v2H8V8zm0 3h2v2H8v-2zm-1 2H5v-2h2v2zm0-3H5V8h2v2zm9 7H8v-2h8v2zm0-4h-2v-2h2v2zm0-3h-2V8h2v2zm3 3h-2v-2h2v2zm0-3h-2V8h2v2z\" fill=\"currentColor\"/>","width":24,"height":24},{"icon":"sharp-keyboard-arrow-down","svg":"<path d=\"M7.41 8.59L12 13.17l4.59-4.58L18 10l-6 6l-6-6l1.41-1.41z\" fill=\"currentColor\"/>","width":24,"height":24},{"icon":"sharp-keyboard-arrow-left","svg":"<path d=\"M15.41 16.59L10.83 12l4.58-4.59L14 6l-6 6l6 6l1.41-1.41z\" fill=\"currentColor\"/>","width":24,"height":24},{"icon":"sharp-keyboard-arrow-right","svg":"<path d=\"M8.59 16.59L13.17 12L8.59 7.41L10 6l6 6l-6 6l-1.41-1.41z\" fill=\"currentColor\"/>","width":24,"height":24},{"icon":"sharp-keyboard-arrow-up","svg":"<path d=\"M7.41 15.41L12 10.83l4.59 4.58L18 14l-6-6l-6 6l1.41 1.41z\" fill=\"currentColor\"/>","width":24,"height":24},{"icon":"sharp-keyboard-backspace","svg":"<path d=\"M21 11H6.83l3.58-3.59L9 6l-6 6l6 6l1.41-1.41L6.83 13H21v-2z\" fill=\"currentColor\"/>","width":24,"height":24},{"icon":"sharp-keyboard-capslock","svg":"<path d=\"M12 8.41L16.59 13L18 11.59l-6-6l-6 6L7.41 13L12 8.41zM6 18h12v-2H6v2z\" fill=\"currentColor\"/>","width":24,"height":24},{"icon":"sharp-keyboard-hide","svg":"<path d=\"M22 3H2.01L2 17h20V3zM11 6h2v2h-2V6zm0 3h2v2h-2V9zM8 6h2v2H8V6zm0 3h2v2H8V9zm-1 2H5V9h2v2zm0-3H5V6h2v2zm9 7H8v-2h8v2zm0-4h-2V9h2v2zm0-3h-2V6h2v2zm3 3h-2V9h2v2zm0-3h-2V6h2v2zm-7 15l4-4H8l4 4z\" fill=\"currentColor\"/>","width":24,"height":24},{"icon":"sharp-keyboard-return","svg":"<path d=\"M19 7v4H5.83l3.58-3.59L8 6l-6 6l6 6l1.41-1.41L5.83 13H21V7h-2z\" fill=\"currentColor\"/>","width":24,"height":24},{"icon":"sharp-keyboard-tab","svg":"<path d=\"M11.59 7.41L15.17 11H1v2h14.17l-3.59 3.59L13 18l6-6l-6-6l-1.41 1.41zM20 6v12h2V6h-2z\" fill=\"currentColor\"/>","width":24,"height":24},{"icon":"sharp-keyboard-voice","svg":"<path d=\"M12 15c1.66 0 2.99-1.34 2.99-3L15 6c0-1.66-1.34-3-3-3S9 4.34 9 6v6c0 1.66 1.34 3 3 3zm5.3-3c0 3-2.54 5.1-5.3 5.1S6.7 15 6.7 12H5c0 3.42 2.72 6.23 6 6.72V22h2v-3.28c3.28-.48 6-3.3 6-6.72h-1.7z\" fill=\"currentColor\"/>","width":24,"height":24},{"icon":"sharp-king-bed","svg":"<path d=\"M20 10V5H4v5H2v7h1.33L4 19h1l.67-2h12.67l.66 2h1l.67-2H22v-7h-2zm-9 0H6V7h5v3zm7 0h-5V7h5v3z\" fill=\"currentColor\"/>","width":24,"height":24},{"icon":"sharp-kitchen","svg":"<path d=\"M20 2.01L4 2v20h16V2.01zM18 20H6v-9.02h12V20zm0-11H6V4h12v5zM8 5h2v3H8V5zm0 7h2v5H8v-5z\" fill=\"currentColor\"/>","width":24,"height":24}]}